{
    "sourceFile": "my-portfolio/src/pages/MenuPage/Header.jsx",
    "activeCommit": 0,
    "commits": [
        {
            "activePatchIndex": 3,
            "patches": [
                {
                    "date": 1756561014369,
                    "content": "Index: \n===================================================================\n--- \n+++ \n"
                },
                {
                    "date": 1756561031070,
                    "content": "Index: \n===================================================================\n--- \n+++ \n@@ -23,9 +23,9 @@\n         <H.NavLow>\r\n           <H.NavbarLink to=\"/header/fth-menu\">4thMenu</H.NavbarLink>\r\n         </H.NavLow>\r\n         <H.NavLow>\r\n-          <H.NavbarLink to=\"/header/timer-menu\">Timer Menu</H.NavbarLink>\r\n+          <H.NavbarLink to=\"/header/timer-menu\">Timer</H.NavbarLink>\r\n         </H.NavLow>\r\n       </H.Nav>\r\n       <Outlet />\r\n     </H.Header>\r\n"
                },
                {
                    "date": 1756561580200,
                    "content": "Index: \n===================================================================\n--- \n+++ \n@@ -11,9 +11,9 @@\n         {/* <H.NavLow>\r\n           <H.NavbarLink to=\"/header/main-home\">Home</H.NavbarLink>\r\n         </H.NavLow> */}\r\n         <H.NavLow>\r\n-          <H.NavbarLink to=\"/header/fst-menu\">1stMenu</H.NavbarLink>\r\n+          <H.NavbarLink to=\"/header/about\">About Me</H.NavbarLink>\r\n         </H.NavLow>\r\n         <H.NavLow>\r\n           <H.NavbarLink to=\"/header/snd-menu\">2ndMenu</H.NavbarLink>\r\n         </H.NavLow>\r\n"
                },
                {
                    "date": 1756561749567,
                    "content": "Index: \n===================================================================\n--- \n+++ \n@@ -7,12 +7,12 @@\n   return (\r\n     <H.Header>\r\n     <DropContainer/>\r\n       <H.Nav>\r\n-        {/* <H.NavLow>\r\n-          <H.NavbarLink to=\"/header/main-home\">Home</H.NavbarLink>\r\n-        </H.NavLow> */}\r\n         <H.NavLow>\r\n+          <H.NavbarLink to=\"/\">Home</H.NavbarLink>\r\n+        </H.NavLow>\r\n+        <H.NavLow>\r\n           <H.NavbarLink to=\"/header/about\">About Me</H.NavbarLink>\r\n         </H.NavLow>\r\n         <H.NavLow>\r\n           <H.NavbarLink to=\"/header/snd-menu\">2ndMenu</H.NavbarLink>\r\n"
                }
            ],
            "date": 1756561014369,
            "name": "Commit-0",
            "content": "import React from \"react\";\r\nimport { Outlet } from \"react-router-dom\";\r\nimport * as H from \"./Header.styled.js\";\r\nimport { DropContainer } from \"../Dropdown/DropContainer.jsx\";\r\n\r\nexport const Header = () => {\r\n  return (\r\n    <H.Header>\r\n    <DropContainer/>\r\n      <H.Nav>\r\n        {/* <H.NavLow>\r\n          <H.NavbarLink to=\"/header/main-home\">Home</H.NavbarLink>\r\n        </H.NavLow> */}\r\n        <H.NavLow>\r\n          <H.NavbarLink to=\"/header/fst-menu\">1stMenu</H.NavbarLink>\r\n        </H.NavLow>\r\n        <H.NavLow>\r\n          <H.NavbarLink to=\"/header/snd-menu\">2ndMenu</H.NavbarLink>\r\n        </H.NavLow>\r\n        <H.NavLow>\r\n          <H.NavbarLink to=\"/header/trd-menu\">3rdMenu</H.NavbarLink>\r\n        </H.NavLow>\r\n        <H.NavLow>\r\n          <H.NavbarLink to=\"/header/fth-menu\">4thMenu</H.NavbarLink>\r\n        </H.NavLow>\r\n        <H.NavLow>\r\n          <H.NavbarLink to=\"/header/timer-menu\">Timer Menu</H.NavbarLink>\r\n        </H.NavLow>\r\n      </H.Nav>\r\n      <Outlet />\r\n    </H.Header>\r\n  );\r\n};\r\n"
        }
    ]
}